scholaris/__init__.py
scholaris/_modidx.py
scholaris/core.py
scholaris/ui.py
scholaris-0.0.3.dist-info/LICENSE
scholaris-0.0.3.dist-info/METADATA
scholaris-0.0.3.dist-info/WHEEL
scholaris-0.0.3.dist-info/entry_points.txt
scholaris-0.0.3.dist-info/top_level.txt
scholaris-0.0.3.dist-info/RECORD
