Metadata-Version: 2.1
Name: scholaris
Version: 0.0.3
Summary: A Python package to set up an advanced research assistant leveraging function calling capabilities with LLMs on your local computer
Home-page: https://github.com/nicomarr/scholaris
Author: Nico Marr
Author-email: nico_marr@outlook.com
License: Apache Software License 2.0
Keywords: nbdev jupyter notebook python ollama llm
Classifier: Development Status :: 4 - Beta
Classifier: Intended Audience :: Developers
Classifier: Natural Language :: English
Classifier: Programming Language :: Python :: 3.7
Classifier: Programming Language :: Python :: 3.8
Classifier: Programming Language :: Python :: 3.9
Classifier: Programming Language :: Python :: 3.10
Classifier: Programming Language :: Python :: 3.11
Classifier: Programming Language :: Python :: 3.12
Classifier: License :: OSI Approved :: Apache Software License
Requires-Python: >=3.7
License-File: LICENSE
Requires-Dist: ollama
Requires-Dist: requests
Requires-Dist: PyPDF2
Requires-Dist: tqdm
Provides-Extra: dev
Requires-Dist: nbdev; extra == "dev"
